[
  {
    "episodeTitle": "ゆとりを持つ意識",
    "storyType": 3,
    "episodeOrder": 81,
    "episodeDetailAssetSource": "scenes/141981_6f662676348788e0ccb89ad1.bin?sv=2023-11-03&se=2026-10-20T15%3A22%3A55Z&sr=b&sp=r&sig=WZvKZ2kID4CS1%2FUkj9xZ8zLbS1z0KX1CrAvMpMhAv%2Bo%3D"
  },
  {
    "episodeTitle": "ゆったりにつき、多忙",
    "storyType": 3,
    "episodeOrder": 82,
    "episodeDetailAssetSource": "scenes/141982_2ea524cfb6be23e144a58b56.bin?sv=2023-11-03&se=2026-10-20T15%3A22%3A55Z&sr=b&sp=r&sig=opf7vOrebRzAza7lIeUyNUY%2FXIMANhvScuDnguTGIhk%3D"
  }
]